mailchimp_marketing/__init__.py
mailchimp_marketing/api_client.py
mailchimp_marketing/configuration.py
mailchimp_marketing/rest.py
mailchimp_marketing/api/__init__.py
mailchimp_marketing/api/account_export_api.py
mailchimp_marketing/api/account_exports_api.py
mailchimp_marketing/api/activity_feed_api.py
mailchimp_marketing/api/authorized_apps_api.py
mailchimp_marketing/api/automations_api.py
mailchimp_marketing/api/batch_webhooks_api.py
mailchimp_marketing/api/batches_api.py
mailchimp_marketing/api/campaign_folders_api.py
mailchimp_marketing/api/campaigns_api.py
mailchimp_marketing/api/connected_sites_api.py
mailchimp_marketing/api/conversations_api.py
mailchimp_marketing/api/customer_journeys_api.py
mailchimp_marketing/api/ecommerce_api.py
mailchimp_marketing/api/facebook_ads_api.py
mailchimp_marketing/api/file_manager_api.py
mailchimp_marketing/api/landing_pages_api.py
mailchimp_marketing/api/lists_api.py
mailchimp_marketing/api/ping_api.py
mailchimp_marketing/api/reporting_api.py
mailchimp_marketing/api/reports_api.py
mailchimp_marketing/api/root_api.py
mailchimp_marketing/api/search_campaigns_api.py
mailchimp_marketing/api/search_members_api.py
mailchimp_marketing/api/template_folders_api.py
mailchimp_marketing/api/templates_api.py
mailchimp_marketing/api/verified_domains_api.py
mailchimp_marketing-3.0.74.dist-info/LICENSE
mailchimp_marketing-3.0.74.dist-info/METADATA
mailchimp_marketing-3.0.74.dist-info/WHEEL
mailchimp_marketing-3.0.74.dist-info/top_level.txt
mailchimp_marketing-3.0.74.dist-info/RECORD
